ece2072_assignment_skeleton/components.v
/*
Monash University ECE2072: Assignment 

Please enter your name and student ID:

*/

`timescale 1ns/1ns

// Sign extender module-------------------------------------------------

module sign_extend(in,ext);

input[8:0] in;
output reg[15:0] ext;

always @(in)
begin
if (in[8] == 1'b0) begin
        ext <= {7'b0000000, in}; // Positive number, extend with zeros
    end 
else begin
        ext <= {7'b1111111, in}; // Negative number, extend with ones
end
end

endmodule

// Tick FSM Module----------------------------------------------------

module tick_FSM(rst, clk, enable, tick);

input  clk,enable,rst;
output  [3:0] tick;

// Define state enumeration
parameter S0 = 4'b0001;
parameter S1 = 4'b0010;
parameter S2 = 4'b0100;
parameter S3 = 4'b1000;
parameter SI = 4'b0000;

// Define state register
reg [3:0] current_state, next_state,reg1;

//Outputs
assign tick=current_state;

// FSM logic
always @(negedge clk ) begin
    
    if ( rst==1'b1) begin

       
        current_state = SI;
    end 

    else if (enable) begin
        case (current_state)
            SI: next_state <= S0;
            S0: next_state <= S1;
            S1: next_state <= S2;
            S2: next_state <= S3;
            S3: next_state <= S0;
            default: next_state <= S0;
        endcase
    end
end

// State register update
always @(posedge clk) begin
    if (enable & ~rst) begin
        current_state <= next_state;
    end
end

endmodule

// ALU module -----------------------------------------------------
module alu(input_a, input_b,alu_op,result);
// InPut Ports
input [15:0] input_a, input_b;
input [2:0]alu_op;
output reg [15:0]result;

//Internal wires
wire [15:0] result_add,result_sub,result_lshift,result_rshift,result_mul;

//Generate Intermideate results
assign #1 result_add =input_a+input_b;
assign #1 result_sub =input_a -input_b;
assign #1 result_mul =input_a * input_b;
assign #1 result_lshift =input_b << 1;
assign #1 result_rshift =input_b >> 1;

//Send correct result according to opcode
  always @(*)
  begin

    case (alu_op)
         3'b000     : result =result_add;
         3'b001     : result=result_sub;
         3'b010     : result =result_mul;
         3'b011     : result=result_rshift;
         3'b100     : result=result_lshift;
         default : result=16'd0;

    endcase
  end


endmodule 

//Multiplexer module----------------------------------------------------------

module multiplexer(SignExtDin, R0, R1, R2, R3, R4, R5, R6, R7, G, sel, Bus);

//input-output ports
input [15:0] SignExtDin, R0, R1, R2, R3, R4, R5, R6, R7, G;
input [3:0]sel;
output reg[15:0] Bus;

always @(*) begin
    case (sel)
        4'b0000: Bus = R0;
        4'b0001: Bus = R1;
        4'b0010: Bus = R2;
        4'b0011: Bus = R3;
        4'b0100: Bus = R4;
        4'b0101: Bus = R5;
        4'b0110: Bus = R6;
        4'b0111: Bus = R7;
        4'b1000: Bus = SignExtDin;
        4'b1001: Bus = G;
        default: Bus = 16'd0; // Default case (optional)
    endcase
end

endmodule

//Register_9 moduel---------------------------------------------------------
module register_9(r_in, enable, clk, Q, rst);

	parameter N = 9;
    //Input-Output ports
    input [N-1:0] r_in;
    input enable,clk,rst;
    output [N-1:0]Q;
    reg[N-1:0] register_9;

    assign #1 Q = register_9;

    //Register  update and reset logic
    always @(negedge clk)  begin

        if(rst)
        begin
           #1
           register_9 <= 9'd0;   // Reset the register
        end
        else 
        begin
           if(enable) 
             begin
             #1
             register_9 <= r_in; // Update the register 
             end

        end
    end
endmodule

//Register_16 module-------------------------------------------

module register_16(r_in, enable, clk, Q, rst);

	parameter N = 16;
 // Input-Output ports
    input [N-1:0] r_in;
    input enable,clk,rst;
    output [N-1:0]Q;

    reg[N-1:0] register_16;  // 16bit Register 

    assign #1 Q = register_16; // Assign output

   // Register update and resert Logic 
    always @(negedge clk)  begin

        if(rst)
        begin
           #1
           register_16 <= 16'd0;  // Reset the register
        end
        else 
        begin
           if(enable) 
             begin
             #1
             register_16 <= r_in;  //Update the register
             end

        end
    end
endmodule

//-------------------------------------------------------EOC-------------------------------------------------------------------

ece2072_assignment_skeleton/proc.v
/*
Monash University ECE2072: Assignment 
This file contains Verilog code to implement individual the CPU.

Please enter your student ID:

*/
`include "components.v"
`timescale 1ns/1ns

module simple_proc(clk, rst, din, bus, R0, R1, R2, R3, R4, R5, R6, R7,TICK_V);
    // inputs and outputs:
    input clk,rst;
    input [8:0]din;
    output [15:0]bus;
    output [15:0]R0, R1, R2, R3, R4, R5, R6, R7 ;
    output[3:0]TICK_V;


    // declare wires:
     wire [15:0]BUS;
     wire[15:0] W_R0,W_R1,W_R2,W_R3,W_R4,W_R5,W_R6,W_R7,W_G,W_A,ALU_Result;
     wire [8:0]W_IR;
     wire [15:0]Sign_extender;
     wire[8:0] IR;
     wire [3:0]Tick;
     reg R0_enable,R1_enable,R2_enable,R3_enable,R4_enable,R5_enable,R6_enable,R7_enable,G_enable,IR_enable,A_enable,Tick_enable;
     reg [3:0]Mux_sel;
     reg [2:0]ALU_OP;

     assign TICK_V =Tick;
     assign R0=W_R0;
     assign R1=W_R1;
     assign R2=W_R2;
     assign R3=W_R3;
     assign R4=W_R4;
     assign R5=W_R5;
     assign R6=W_R6;
     assign R7=W_R7;
     assign bus =BUS;

  



    // instantiate regiSign extnder
    sign_extend sign_extend1(din,Sign_extender);


    // instantiate registers:
    register_16 r0(BUS,R0_enable,clk,W_R0,rst);
    register_16 r1(BUS,R1_enable,clk,W_R1,rst);
    register_16 r2(BUS,R2_enable,clk,W_R2,rst);
    register_16 r3(BUS,R3_enable,clk,W_R3,rst);
    register_16 r4(BUS,R4_enable,clk,W_R4,rst);
    register_16 r5(BUS,R5_enable,clk,W_R5,rst);
    register_16 r6(BUS,R6_enable,clk,W_R6,rst);
    register_16 r7(BUS,R7_enable,clk,W_R7,rst);
    register_16 a(BUS,A_enable,clk,W_A,rst);
    register_16 g(ALU_Result,G_enable,clk,W_G,rst);
    register_9 ir (din,IR_enable,clk,W_IR,rst);
    
    // instantiate Multiplexer:
    multiplexer multiplexer1(Sign_extender,W_R0,W_R1,W_R2,W_R3,W_R4,W_R5,W_R6,W_R7,W_G,Mux_sel,BUS);
    
    // nstantiate ALU:
    
    alu alu1(W_A,BUS,ALU_OP,ALU_Result);
    // instantiate tick counter:
    tick_FSM tick_FSM1(rst,clk,1'b1,Tick);
    
    // TODO: define control unit:
    always @(Tick) begin

       IR_enable=1'b0;

        R0_enable=1'b0;
        R0_enable=1'b0;
        R1_enable=1'b0;
        R2_enable=1'b0;
        R3_enable=1'b0;
        R4_enable=1'b0;
        R5_enable=1'b0;
        R6_enable=1'b0;
        R7_enable=1'b0;
        G_enable=1'b0;
        A_enable=1'b0;
        Mux_sel =4'b1111;
        ALU_OP =3'b111;

       
        case (Tick)
                4'b0001:
                begin
                    IR_enable=1'b1;

                    R0_enable=1'b0;
                    R0_enable=1'b0;
                    R1_enable=1'b0;
                    R2_enable=1'b0;
                    R3_enable=1'b0;
                    R4_enable=1'b0;
                    R5_enable=1'b0;
                    R6_enable=1'b0;
                    R7_enable=1'b0;
                    G_enable=1'b0;
                    A_enable=1'b0;

                     Mux_sel =4'b1111;
                     ALU_OP =3'b111;

  
                end
            
                4'b0010:
                begin

                    IR_enable=1'b0;
                    R0_enable=1'b0;
                    R0_enable=1'b0;
                    R1_enable=1'b0;
                    R2_enable=1'b0;
                    R3_enable=1'b0;
                    R4_enable=1'b0;
                    R5_enable=1'b0;
                    R6_enable=1'b0;
                    R7_enable=1'b0;
                    G_enable=1'b0;
                    A_enable=1'b1;

                     Mux_sel ={2'b00,W_IR[5:3]};
                     ALU_OP =3'b111;
                    
                end
            
                4'b0100:
                begin
                    IR_enable=1'b0;
                    R0_enable=1'b0;
                    R0_enable=1'b0;
                    R1_enable=1'b0;
                    R2_enable=1'b0;
                    R3_enable=1'b0;
                    R4_enable=1'b0;
                    R5_enable=1'b0;
                    R6_enable=1'b0;
                    R7_enable=1'b0;
                    G_enable=1'b1;
                    A_enable=1'b0;

                    


                    case(W_IR[8:6])

                        3'b000:
                        begin
                            ALU_OP=3'b111;
                            Mux_sel =4'b1111;

                        end

                        3'b001:
                        begin

                            ALU_OP=3'b000;
                            Mux_sel ={2'b00,W_IR[2:0]};

                        end
                        3'b010:
                        begin
                            ALU_OP=3'b000;
                            Mux_sel=4'b1000;


                        end

                         3'b011:
                        begin
                               ALU_OP=3'b001;
                               Mux_sel ={2'b00,W_IR[2:0]};

                        end

                         3'b100:
                        begin
                               ALU_OP=3'b010;
                               Mux_sel ={2'b00,W_IR[2:0]};

                        end

                        3'b101:
                        begin
                               ALU_OP=3'b011;
                                Mux_sel =4'b1111;

                        end
                        3'b110:
                        begin
                               ALU_OP=3'b100;
                                Mux_sel =4'b1111;

                        end
                        3'b111:
                        begin
                               ALU_OP=3'b111;
                               Mux_sel=4'b1000;


                        end



                    endcase
                    
                    
                end
            
                4'b1000:
                begin

                    IR_enable=1'b0;
                    R0_enable=1'b0;
                    R0_enable=1'b0;
                    R1_enable=1'b0;
                    R2_enable=1'b0;
                    R3_enable=1'b0;
                    R4_enable=1'b0;
                    R5_enable=1'b0;
                    R6_enable=1'b0;
                    R7_enable=1'b0;
                    G_enable=1'b0;
                    A_enable=1'b0;

                    Mux_sel =4'b1001;
                    ALU_OP =3'b111;

                    case(W_IR[5:3])

                        3'b000:
                        begin
                            R0_enable=1'b1;

                        end

                        3'b001:
                        begin

                             R1_enable=1'b1;

                        end
                        3'b010:
                        begin
                             R2_enable=1'b1;

                        end

                         3'b011:
                        begin
                            R3_enable=1'b1;

                        end

                         3'b100:
                        begin
                                R4_enable=1'b1;

                        end

                        3'b101:
                        begin
                                R5_enable=1'b1;

                        end
                        3'b110:
                        begin
                                R6_enable=1'b1;

                        end
                        3'b111:
                        begin
                                R7_enable=1'b1;

                        end



                    endcase
                    

                    


                    
                end
            
            default:
                begin
                    // TODO
                end

        endcase

    end

endmodule

ece2072_assignment_skeleton/proc_tb.v

`include "proc.v"
`timescale 1ns/1ns
/*
Monash University ECE2072: Assignment 
This file contains a Verilog test bench to test the correctness of the processor.

Please enter your student ID:

*/
module proc_tb;
    
    
    reg clk=0;
    reg rst;
    reg[8:0]din;
    wire[3:0]TICK;

    wire [15:0] bus, R0, R1, R2, R3, R4, R5, R6, R7;

    always #5 clk = ~clk;

    simple_proc simple_proc1(clk, rst, din, bus, R0, R1, R2, R3, R4, R5, R6, R7,TICK);



      initial 
    begin
        $dumpfile("cpu_tb.vcd");
        $dumpvars(1, simple_proc1);
        
        
    end


    initial begin
     clk=0   ;

    $display("clk :",clk);
    $display("rst :",rst);
     $display("tick :%b",TICK);
    $display("din :%b",din);
    $display("bus :%b",bus);
    $display("R0 :",R0);
    $display("R0 :",R1);
    $display("R0 :",R2);
    $display("R0 :",R3);
    $display("R0 :",R4);
    $display("R0 :",R5);
    $display("R0 :",R6);
    $display("R0 :",R7);

    rst=1'b1;
  
     #6  

    $display("clk :",clk);
    $display("rst :",rst);
     $display("tick :%b",TICK);
    $display("din :%b",din);
    $display("bus :%b",bus);
    $display("R0 :",R0);
    $display("R0 :",R1);
    $display("R0 :",R2);
    $display("R0 :",R3);
    $display("R0 :",R4);
    $display("R0 :",R5);
    $display("R0 :",R6);
    $display("R0 :",R7);

    //INS1------------------------------
    rst=1'b0;
    din=9'b010100011;
     
    #10

    
    $display("clk :",clk);
    $display("rst :",rst);
    $display("tick :%b",TICK);
    $display("din %b:",din);
    $display("bus :%b",bus);
    $display("R0 :",R0);
    $display("R0 :",R1);
    $display("R0 :",R2);
    $display("R0 :",R3);
    $display("R0 :",R4);
    $display("R0 :",R5);
    $display("R0 :",R6);
    $display("R0 :",R7);

   
    #10

    
    $display("clk :",clk);
    $display("rst :",rst);
     $display("tick :%b",TICK);
    $display("din :%b",din);
    $display("bus :%b",bus);
    $display("R0 :",R0);
    $display("R0 :",R1);
    $display("R0 :",R2);
    $display("R0 :",R3);
    $display("R0 :",R4);
    $display("R0 :",R5);
    $display("R0 :",R6);
    $display("R0 :",R7);


    din=9'b000000011;
    #10

    
    $display("clk :",clk);
    $display("rst :",rst);
     $display("tick :%b",TICK);
    $display("din :%b",din);
    $display("bus :%b",bus);
    $display("R0 :",R0);
    $display("R0 :",R1);
    $display("R0 :",R2);
    $display("R0 :",R3);
    $display("R0 :",R4);
    $display("R0 :",R5);
    $display("R0 :",R6);
    $display("R0 :",R7);



   #10

    
    $display("clk :",clk);
    $display("rst :",rst);
     $display("tick :%b",TICK);
    $display("din :%b",din);
    $display("bus :%b",bus);
    $display("R0 :",R0);
    $display("R0 :",R1);
    $display("R0 :",R2);
    $display("R0 :",R3);
    $display("R0 :",R4);
    $display("R0 :",R5);
    $display("R0 :",R6);
    $display("R0 :",R7);

   //INS 2------------------------------------------
   din=9'b010101011;
    #20

   din=9'b000000010;

    #30

    
    $display("clk :",clk);
    $display("rst :",rst);
     $display("tick :%b",TICK);
    $display("din :%b",din);
    $display("bus :%b",bus);
    $display("R0 :",R0);
    $display("R0 :",R1);
    $display("R0 :",R2);
    $display("R0 :",R3);
    $display("R0 :",R4);
    $display("R0 :",R5);
    $display("R0 :",R6);
    $display("R0 :",R7);
    
    din=9'b001101100;

    #50

    $display("clk :",clk);
    $display("rst :",rst);
     $display("tick :%b",TICK);
    $display("din :%b",din);
    $display("bus :%b",bus);
    $display("R0 :",R0);
    $display("R0 :",R1);
    $display("R0 :",R2);
    $display("R0 :",R3);
    $display("R0 :",R4);
    $display("R0 :",R5);
    $display("R0 :",R6);
    $display("R0 :",R7);





    
    
    $finish;



    end

    


   

endmodule

ece2072_assignment_skeleton/cpu_tb.vcd
$date
	Mon Oct  9 18:02:43 2023
$end
$version
	Icarus Verilog
$end
$timescale
	1ns
$end
$scope module proc_tb $end
$scope module simple_proc1 $end
$var wire 16 ! R0 [15:0] $end
$var wire 16 " R1 [15:0] $end
$var wire 16 # R2 [15:0] $end
$var wire 16 $ R3 [15:0] $end
$var wire 16 % R4 [15:0] $end
$var wire 16 & R5 [15:0] $end
$var wire 16 ' R6 [15:0] $end
$var wire 16 ( R7 [15:0] $end
$var wire 4 ) TICK_V [3:0] $end
$var wire 16 * bus [15:0] $end
$var wire 1 + clk $end
$var wire 9 , din [8:0] $end
$var wire 1 - rst $end
$var wire 16 . W_R7 [15:0] $end
$var wire 16 / W_R6 [15:0] $end
$var wire 16 0 W_R5 [15:0] $end
$var wire 16 1 W_R4 [15:0] $end
$var wire 16 2 W_R3 [15:0] $end
$var wire 16 3 W_R2 [15:0] $end
$var wire 16 4 W_R1 [15:0] $end
$var wire 16 5 W_R0 [15:0] $end
$var wire 9 6 W_IR [8:0] $end
$var wire 16 7 W_G [15:0] $end
$var wire 16 8 W_A [15:0] $end
$var wire 4 9 Tick [3:0] $end
$var wire 16 : Sign_extender [15:0] $end
$var wire 16 ; BUS [15:0] $end
$var wire 16 < ALU_Result [15:0] $end
$var reg 3 = ALU_OP [2:0] $end
$var reg 1 > A_enable $end
$var reg 1 ? G_enable $end
$var reg 1 @ IR_enable $end
$var reg 4 A Mux_sel [3:0] $end
$var reg 1 B R0_enable $end
$var reg 1 C R1_enable $end
$var reg 1 D R2_enable $end
$var reg 1 E R3_enable $end
$var reg 1 F R4_enable $end
$var reg 1 G R5_enable $end
$var reg 1 H R6_enable $end
$var reg 1 I R7_enable $end
$upscope $end
$upscope $end
$enddefinitions $end
#0
$dumpvars
0I
0H
0G
0F
0E
0D
0C
0B
b1111 A
0@
0?
0>
b111 =
b0 <
b0 ;
bx :
b0 9
bx 8
bx 7
bx 6
bx 5
bx 4
bx 3
bx 2
bx 1
bx 0
bx /
bx .
1-
bx ,
0+
b0 *
b0 )
bx (
bx '
bx &
bx %
bx $
bx #
bx "
bx !
$end
#2
b0 !
b0 5
b0 "
b0 4
b0 #
b0 3
b0 $
b0 2
b0 %
b0 1
b0 &
b0 0
b0 '
b0 /
b0 (
b0 .
b0 8
b0 7
b0 6
#5
1+
#6
b10100011 :
b10100011 ,
0-
#10
0+
#15
1@
b1 )
b1 9
1+
#20
0+
#22
b10100011 6
#25
b100 A
1>
0@
b10 )
b10 9
1+
#26
b11 :
b11 ,
#30
0+
#35
b11 *
b11 ;
b0 =
1?
b1000 A
0>
b100 )
b100 9
1+
#36
b11 <
#40
0+
#42
b11 7
#45
b0 <
1F
b111 =
b1001 A
0?
b1000 )
b1000 9
1+
#46
b10101011 :
b10101011 ,
#50
0+
#52
b11 %
b11 1
#55
b0 *
b0 ;
1@
b1111 A
0F
b1 )
b1 9
1+
#60
0+
#62
b10101011 6
#65
b101 A
1>
0@
b10 )
b10 9
1+
#66
b10 :
b10 ,
#70
0+
#75
b10 *
b10 ;
b0 =
1?
b1000 A
0>
b100 )
b100 9
1+
#76
b10 <
#80
0+
#82
b10 7
#85
b0 <
1G
b111 =
b1001 A
0?
b1000 )
b1000 9
1+
#90
0+
#92
b10 &
b10 0
#95
b0 *
b0 ;
1@
b1111 A
0G
b1 )
b1 9
1+
#96
b1101100 :
b1101100 ,
#100
0+
#102
b1101100 6
#105
b10 *
b10 ;
b101 A
1>
0@
b10 )
b10 9
1+
#110
0+
#112
b10 8
#115
b100 <
b11 *
b11 ;
b0 =
1?
b100 A
0>
b100 )
b100 9
1+
#116
b101 <
#120
0+
#122
b101 7
#125
b0 <
b101 *
b101 ;
1G
b111 =
b1001 A
0?
b1000 )
b1000 9
1+
#130
0+
#132
b101 &
b101 0
#135
b0 *
b0 ;
1@
b1111 A
0G
b1 )
b1 9
1+
#140
0+
#145
b101 *
b101 ;
b101 A
1>
0@
b10 )
b10 9
1+
